numpy_posit.cpython-34m.so
numpy/__config__.py
numpy/__init__.py
numpy/_import_tools.py
numpy/LICENSE.txt
numpy/setup.py
numpy/_globals.py
numpy/_distributor_init.py
numpy/conftest.py
numpy/ctypeslib.py
numpy/dual.py
numpy/version.py
numpy/add_newdocs.py
numpy/matlib.py
numpy/lib/_iotools.py
numpy/lib/arrayterator.py
numpy/lib/_version.py
numpy/lib/__init__.py
numpy/lib/histograms.py
numpy/lib/financial.py
numpy/lib/info.py
numpy/lib/format.py
numpy/lib/shape_base.py
numpy/lib/nanfunctions.py
numpy/lib/twodim_base.py
numpy/lib/arraysetops.py
numpy/lib/setup.py
numpy/lib/user_array.py
numpy/lib/type_check.py
numpy/lib/index_tricks.py
numpy/lib/arraypad.py
numpy/lib/scimath.py
numpy/lib/polynomial.py
numpy/lib/utils.py
numpy/lib/function_base.py
numpy/lib/ufunclike.py
numpy/lib/_datasource.py
numpy/lib/mixins.py
numpy/lib/recfunctions.py
numpy/lib/stride_tricks.py
numpy/lib/npyio.py
numpy/lib/tests/test_index_tricks.py
numpy/lib/tests/test__version.py
numpy/lib/tests/test_regression.py
numpy/lib/tests/test_stride_tricks.py
numpy/lib/tests/test_io.py
numpy/lib/tests/__init__.py
numpy/lib/tests/test_arraypad.py
numpy/lib/tests/test__iotools.py
numpy/lib/tests/test_histograms.py
numpy/lib/tests/test_arrayterator.py
numpy/lib/tests/test_type_check.py
numpy/lib/tests/test_shape_base.py
numpy/lib/tests/test_financial.py
numpy/lib/tests/test_recfunctions.py
numpy/lib/tests/test__datasource.py
numpy/lib/tests/test_function_base.py
numpy/lib/tests/test_twodim_base.py
numpy/lib/tests/test_nanfunctions.py
numpy/lib/tests/test_polynomial.py
numpy/lib/tests/test_ufunclike.py
numpy/lib/tests/test_utils.py
numpy/lib/tests/test_mixins.py
numpy/lib/tests/test_packbits.py
numpy/lib/tests/test_format.py
numpy/lib/tests/test_arraysetops.py
numpy/lib/tests/data/win64python2.npy
numpy/lib/tests/data/py3-objarr.npz
numpy/lib/tests/data/py2-objarr.npz
numpy/lib/tests/data/py3-objarr.npy
numpy/lib/tests/data/python3.npy
numpy_posit-1.15.2.0.0.1.dev2.dist-info/top_level.txt
numpy_posit-1.15.2.0.0.1.dev2.dist-info/RECORD
numpy_posit-1.15.2.0.0.1.dev2.dist-info/WHEEL
numpy_posit-1.15.2.0.0.1.dev2.dist-info/METADATA
numpy_posit-1.15.2.0.0.1.dev2.data/data/lib/python3.4/site-packages/numpy-1.15.2.0.0.1.dev2.dist-info/top_level.txt
numpy_posit-1.15.2.0.0.1.dev2.data/data/lib/python3.4/site-packages/numpy-1.15.2.0.0.1.dev2.dist-info/RECORD
numpy_posit-1.15.2.0.0.1.dev2.data/data/lib/python3.4/site-packages/numpy-1.15.2.0.0.1.dev2.dist-info/WHEEL
numpy_posit-1.15.2.0.0.1.dev2.data/data/lib/python3.4/site-packages/numpy-1.15.2.0.0.1.dev2.dist-info/METADATA
