Metadata-Version: 2.1
Name: numpy-posit
Version: 1.15.2.0.0.1.dev2
Summary: posit (unum type III) integrated NumPy.
Home-page: https://github.com/xman/numpy-posit
Author: SpeedGo Computing
Author-email: shinyee@speedgocomputing.com
License: BSD
Keywords: unum posit numpy
Platform: UNKNOWN
